<?xml version="1.0" encoding="utf-8" ?>
<dwsync>
<file name="shCore.css" server="5.51.58.107//var/www/" local="130696302906066701" remote="130714111200000000" Dst="1" />
<file name="shCoreDefault.css" server="5.51.58.107//var/www/" local="130696302904191609" remote="130714111200000000" Dst="1" />
<file name="shCoreDjango.css" server="5.51.58.107//var/www/" local="130696302900285156" remote="130714111200000000" Dst="1" />
<file name="shCoreEclipse.css" server="5.51.58.107//var/www/" local="130696302897282636" remote="130714111200000000" Dst="1" />
<file name="shCoreEmacs.css" server="5.51.58.107//var/www/" local="130696302893409387" remote="130714111200000000" Dst="1" />
<file name="shCoreFadeToGrey.css" server="5.51.58.107//var/www/" local="130696302891525173" remote="130714111200000000" Dst="1" />
<file name="shCoreMDUltra.css" server="5.51.58.107//var/www/" local="130696302886478984" remote="130714111200000000" Dst="1" />
<file name="shCoreMidnight.css" server="5.51.58.107//var/www/" local="130696302885553393" remote="130714111200000000" Dst="1" />
<file name="shCoreRDark.css" server="5.51.58.107//var/www/" local="130696302879670210" remote="130714111200000000" Dst="1" />
<file name="shThemeAppleScript.css" server="5.51.58.107//var/www/" local="130696302879370181" remote="130714111200000000" Dst="1" />
<file name="shThemeDefault.css" server="5.51.58.107//var/www/" local="130696302876315035" remote="130714111200000000" Dst="1" />
<file name="shThemeDjango.css" server="5.51.58.107//var/www/" local="130696302876165047" remote="130714111200000000" Dst="1" />
<file name="shThemeEclipse.css" server="5.51.58.107//var/www/" local="130696302872564785" remote="130714111200000000" Dst="1" />
<file name="shThemeEmacs.css" server="5.51.58.107//var/www/" local="130696302872564785" remote="130714111200000000" Dst="1" />
<file name="shThemeFadeToGrey.css" server="5.51.58.107//var/www/" local="130696302868448470" remote="130714111200000000" Dst="1" />
<file name="shThemeMDUltra.css" server="5.51.58.107//var/www/" local="130696302868070699" remote="130714111200000000" Dst="1" />
<file name="shThemeMidnight.css" server="5.51.58.107//var/www/" local="130696302865709806" remote="130714111200000000" Dst="1" />
<file name="shThemeRDark.css" server="5.51.58.107//var/www/" local="130696302865503017" remote="130714111200000000" Dst="1" />
<file name="shThemeVisualStudio.css" server="5.51.58.107//var/www/" local="130696302863313146" remote="130714111200000000" Dst="1" />
<file name="wrapping.png" server="5.51.58.107//var/www/" local="130696302862820210" remote="130714111200000000" Dst="1" />
</dwsync>